{
  "sections": {
    "image_banner": {
      "type": "image-banner",
      "blocks": {
        "heading": {
          "type": "heading",
          "settings": {
            "heading": "Discover Signature Look: Fashion Forward and Fabulous!",
            "heading_size": "h0"
          }
        },
        "button": {
          "type": "buttons",
          "settings": {
            "button_label_1": "Shop all",
            "button_link_1": "shopify:\/\/collections\/all",
            "button_style_secondary_1": true,
            "button_label_2": "",
            "button_link_2": "",
            "button_style_secondary_2": false
          }
        }
      },
      "block_order": [
        "heading",
        "button"
      ],
      "disabled": true,
      "settings": {
        "image_overlay_opacity": 40,
        "image_height": "large",
        "desktop_content_position": "bottom-center",
        "show_text_box": false,
        "desktop_content_alignment": "center",
        "color_scheme": "scheme-5",
        "image_behavior": "none",
        "mobile_content_alignment": "center",
        "stack_images_on_mobile": false,
        "show_text_below": false
      }
    },
    "hero_banner_slider_hMhRdj": {
      "type": "hero-banner-slider",
      "blocks": {
        "banner_NmdDyR": {
          "type": "banner",
          "settings": {
            "desktop_image": "shopify:\/\/shop_images\/1.png",
            "mobile_image": "shopify:\/\/shop_images\/1.png",
            "banner_caption": "Women's Apparel",
            "banner_heading": "Elevate your wardrobe with our",
            "banner_heading_link_text": "limited-time",
            "banner_heading_link": "#",
            "banner_heading_end_text": "fashion offer!",
            "banner_button_text": "Explore More",
            "banner_button_link": "#",
            "banner_color_scheme": "scheme_1",
            "text_alignment": "left",
            "vertical_alignment": "center",
            "horizantal_alignment": "center",
            "slider_autoplay": "true",
            "slider_autoplay_duration": 2000
          }
        },
        "banner_FchdrT": {
          "type": "banner",
          "settings": {
            "desktop_image": "shopify:\/\/shop_images\/4.png",
            "mobile_image": "shopify:\/\/shop_images\/4.png",
            "banner_caption": "",
            "banner_heading": "",
            "banner_heading_link_text": "limited-time",
            "banner_heading_link": "",
            "banner_heading_end_text": "fashion offer!",
            "banner_button_text": "",
            "banner_button_link": "",
            "banner_color_scheme": "scheme_1",
            "text_alignment": "left",
            "vertical_alignment": "center",
            "horizantal_alignment": "center",
            "slider_autoplay": "true",
            "slider_autoplay_duration": 2000
          }
        },
        "banner_G6GNmM": {
          "type": "banner",
          "settings": {
            "desktop_image": "shopify:\/\/shop_images\/3.png",
            "mobile_image": "shopify:\/\/shop_images\/3.png",
            "banner_caption": "",
            "banner_heading": "",
            "banner_heading_link_text": "limited-time",
            "banner_heading_link": "",
            "banner_heading_end_text": "fashion offer!",
            "banner_button_text": "",
            "banner_button_link": "",
            "banner_color_scheme": "scheme_1",
            "text_alignment": "left",
            "vertical_alignment": "center",
            "horizantal_alignment": "center",
            "slider_autoplay": "true",
            "slider_autoplay_duration": 2000
          }
        }
      },
      "block_order": [
        "banner_NmdDyR",
        "banner_FchdrT",
        "banner_G6GNmM"
      ],
      "settings": {
        "padding_top": 36,
        "padding_bottom": 36
      }
    }
  },
  "order": [
    "image_banner",
    "hero_banner_slider_hMhRdj"
  ]
}
